setup.py
smsapi/__init__.py
smsapi/__main__.py
smsapi/ovh.py
smsapi/utils.py
smsapi.egg-info/PKG-INFO
smsapi.egg-info/SOURCES.txt
smsapi.egg-info/dependency_links.txt
smsapi.egg-info/top_level.txt