Metadata-Version: 1.1
Name: smsapi
Version: 0.11.0
Summary: Use online API to send SMS
Home-page: UNKNOWN
Author: Benjamin Dauvergne
Author-email: bdauvergne@entrouvert.com
License: MIT
Platform: UNKNOWN
Requires: requests
